[{"instance": "kube-prometheus-prometheus-node-exporter.oxn-external-monitoring.svc:9100", "timestamp": 1738187955.417, "sum(rate(node_network_receive_bytes_total[1m]) + rate(node_network_transmit_bytes_total[1m])) by (instance)": 227603918.0813354, "network_bytes": 227603918.0813354, "kubernetes_prometheus_rules": "kubernetes_prometheus_rules", "add_security_context": "NoTreatment", "delay_treatment": "NoTreatment"}, {"instance": "kube-prometheus-prometheus-node-exporter.oxn-external-monitoring.svc:9100", "timestamp": 1738187956.417, "sum(rate(node_network_receive_bytes_total[1m]) + rate(node_network_transmit_bytes_total[1m])) by (instance)": 227576955.97050208, "network_bytes": 227576955.97050208, "kubernetes_prometheus_rules": "kubernetes_prometheus_rules", "add_security_context": "NoTreatment", "delay_treatment": "NoTreatment"}, {"instance": "kube-prometheus-prometheus-node-exporter.oxn-external-monitoring.svc:9100", "timestamp": 1738187957.417, "sum(rate(node_network_receive_bytes_total[1m]) + rate(node_network_transmit_bytes_total[1m])) by (instance)": 227549993.85966873, "network_bytes": 227549993.85966873, "kubernetes_prometheus_rules": "kubernetes_prometheus_rules", "add_security_context": "NoTreatment", "delay_treatment": "NoTreatment"}, {"instance": "kube-prometheus-prometheus-node-exporter.oxn-external-monitoring.svc:9100", "timestamp": 1738187958.417, "sum(rate(node_network_receive_bytes_total[1m]) + rate(node_network_transmit_bytes_total[1m])) by (instance)": 249088330.81155503, "network_bytes": 249088330.81155503, "kubernetes_prometheus_rules": "kubernetes_prometheus_rules", "add_security_context": "NoTreatment", "delay_treatment": "NoTreatment"}, {"instance": "kube-prometheus-prometheus-node-exporter.oxn-external-monitoring.svc:9100", "timestamp": 1738187959.417, "sum(rate(node_network_receive_bytes_total[1m]) + rate(node_network_transmit_bytes_total[1m])) by (instance)": 249061987.30294392, "network_bytes": 249061987.30294392, "kubernetes_prometheus_rules": "kubernetes_prometheus_rules", "add_security_context": "NoTreatment", "delay_treatment": "NoTreatment"}, {"instance": "kube-prometheus-prometheus-node-exporter.oxn-external-monitoring.svc:9100", "timestamp": 1738187960.417, "sum(rate(node_network_receive_bytes_total[1m]) + rate(node_network_transmit_bytes_total[1m])) by (instance)": 227271503.7129002, "network_bytes": 227271503.7129002, "kubernetes_prometheus_rules": "kubernetes_prometheus_rules", "add_security_context": "NoTreatment", "delay_treatment": "NoTreatment"}, {"instance": "kube-prometheus-prometheus-node-exporter.oxn-external-monitoring.svc:9100", "timestamp": 1738187961.417, "sum(rate(node_network_receive_bytes_total[1m]) + rate(node_network_transmit_bytes_total[1m])) by (instance)": 227244956.42178908, "network_bytes": 227244956.42178908, "kubernetes_prometheus_rules": "kubernetes_prometheus_rules", "add_security_context": "NoTreatment", "delay_treatment": "NoTreatment"}, {"instance": "kube-prometheus-prometheus-node-exporter.oxn-external-monitoring.svc:9100", "timestamp": 1738187962.417, "sum(rate(node_network_receive_bytes_total[1m]) + rate(node_network_transmit_bytes_total[1m])) by (instance)": 227218409.13067797, "network_bytes": 227218409.13067797, "kubernetes_prometheus_rules": "kubernetes_prometheus_rules", "add_security_context": "NoTreatment", "delay_treatment": "NoTreatment"}, {"instance": "kube-prometheus-prometheus-node-exporter.oxn-external-monitoring.svc:9100", "timestamp": 1738187963.417, "sum(rate(node_network_receive_bytes_total[1m]) + rate(node_network_transmit_bytes_total[1m])) by (instance)": 248714504.15169707, "network_bytes": 248714504.15169707, "kubernetes_prometheus_rules": "kubernetes_prometheus_rules", "add_security_context": "NoTreatment", "delay_treatment": "NoTreatment"}, {"instance": "kube-prometheus-prometheus-node-exporter.oxn-external-monitoring.svc:9100", "timestamp": 1738187964.417, "sum(rate(node_network_receive_bytes_total[1m]) + rate(node_network_transmit_bytes_total[1m])) by (instance)": 248690125.24836373, "network_bytes": 248690125.24836373, "kubernetes_prometheus_rules": "kubernetes_prometheus_rules", "add_security_context": "NoTreatment", "delay_treatment": "NoTreatment"}, {"instance": "kube-prometheus-prometheus-node-exporter.oxn-external-monitoring.svc:9100", "timestamp": 1738187965.417, "sum(rate(node_network_receive_bytes_total[1m]) + rate(node_network_transmit_bytes_total[1m])) by (instance)": 226916700.62458718, "network_bytes": 226916700.62458718, "kubernetes_prometheus_rules": "kubernetes_prometheus_rules", "add_security_context": "add_security_context", "delay_treatment": "NoTreatment"}, {"instance": "kube-prometheus-prometheus-node-exporter.oxn-external-monitoring.svc:9100", "timestamp": 1738187966.417, "sum(rate(node_network_receive_bytes_total[1m]) + rate(node_network_transmit_bytes_total[1m])) by (instance)": 226892141.58292052, "network_bytes": 226892141.58292052, "kubernetes_prometheus_rules": "kubernetes_prometheus_rules", "add_security_context": "add_security_context", "delay_treatment": "delay_treatment"}, {"instance": "kube-prometheus-prometheus-node-exporter.oxn-external-monitoring.svc:9100", "timestamp": 1738187967.417, "sum(rate(node_network_receive_bytes_total[1m]) + rate(node_network_transmit_bytes_total[1m])) by (instance)": 226867582.54125383, "network_bytes": 226867582.54125383, "kubernetes_prometheus_rules": "kubernetes_prometheus_rules", "add_security_context": "add_security_context", "delay_treatment": "delay_treatment"}, {"instance": "kube-prometheus-prometheus-node-exporter.oxn-external-monitoring.svc:9100", "timestamp": 1738187968.417, "sum(rate(node_network_receive_bytes_total[1m]) + rate(node_network_transmit_bytes_total[1m])) by (instance)": 248320452.8725955, "network_bytes": 248320452.8725955, "kubernetes_prometheus_rules": "kubernetes_prometheus_rules", "add_security_context": "add_security_context", "delay_treatment": "delay_treatment"}, {"instance": "kube-prometheus-prometheus-node-exporter.oxn-external-monitoring.svc:9100", "timestamp": 1738187969.417, "sum(rate(node_network_receive_bytes_total[1m]) + rate(node_network_transmit_bytes_total[1m])) by (instance)": 248301291.12092882, "network_bytes": 248301291.12092882, "kubernetes_prometheus_rules": "kubernetes_prometheus_rules", "add_security_context": "add_security_context", "delay_treatment": "delay_treatment"}, {"instance": "kube-prometheus-prometheus-node-exporter.oxn-external-monitoring.svc:9100", "timestamp": 1738187970.417, "sum(rate(node_network_receive_bytes_total[1m]) + rate(node_network_transmit_bytes_total[1m])) by (instance)": 226568171.89393756, "network_bytes": 226568171.89393756, "kubernetes_prometheus_rules": "kubernetes_prometheus_rules", "add_security_context": "add_security_context", "delay_treatment": "delay_treatment"}, {"instance": "kube-prometheus-prometheus-node-exporter.oxn-external-monitoring.svc:9100", "timestamp": 1738187971.417, "sum(rate(node_network_receive_bytes_total[1m]) + rate(node_network_transmit_bytes_total[1m])) by (instance)": 226549007.6577471, "network_bytes": 226549007.6577471, "kubernetes_prometheus_rules": "kubernetes_prometheus_rules", "add_security_context": "add_security_context", "delay_treatment": "delay_treatment"}, {"instance": "kube-prometheus-prometheus-node-exporter.oxn-external-monitoring.svc:9100", "timestamp": 1738187972.417, "sum(rate(node_network_receive_bytes_total[1m]) + rate(node_network_transmit_bytes_total[1m])) by (instance)": 226529843.42155662, "network_bytes": 226529843.42155662, "kubernetes_prometheus_rules": "kubernetes_prometheus_rules", "add_security_context": "add_security_context", "delay_treatment": "delay_treatment"}, {"instance": "kube-prometheus-prometheus-node-exporter.oxn-external-monitoring.svc:9100", "timestamp": 1738187973.417, "sum(rate(node_network_receive_bytes_total[1m]) + rate(node_network_transmit_bytes_total[1m])) by (instance)": 247865010.2229321, "network_bytes": 247865010.2229321, "kubernetes_prometheus_rules": "kubernetes_prometheus_rules", "add_security_context": "add_security_context", "delay_treatment": "delay_treatment"}, {"instance": "kube-prometheus-prometheus-node-exporter.oxn-external-monitoring.svc:9100", "timestamp": 1738187974.417, "sum(rate(node_network_receive_bytes_total[1m]) + rate(node_network_transmit_bytes_total[1m])) by (instance)": 247882241.11340827, "network_bytes": 247882241.11340827, "kubernetes_prometheus_rules": "kubernetes_prometheus_rules", "add_security_context": "add_security_context", "delay_treatment": "delay_treatment"}, {"instance": "kube-prometheus-prometheus-node-exporter.oxn-external-monitoring.svc:9100", "timestamp": 1738187975.417, "sum(rate(node_network_receive_bytes_total[1m]) + rate(node_network_transmit_bytes_total[1m])) by (instance)": 226215271.90725243, "network_bytes": 226215271.90725243, "kubernetes_prometheus_rules": "kubernetes_prometheus_rules", "add_security_context": "add_security_context", "delay_treatment": "delay_treatment"}, {"instance": "kube-prometheus-prometheus-node-exporter.oxn-external-monitoring.svc:9100", "timestamp": 1738187976.417, "sum(rate(node_network_receive_bytes_total[1m]) + rate(node_network_transmit_bytes_total[1m])) by (instance)": 226232669.78808576, "network_bytes": 226232669.78808576, "kubernetes_prometheus_rules": "kubernetes_prometheus_rules", "add_security_context": "add_security_context", "delay_treatment": "delay_treatment"}, {"instance": "kube-prometheus-prometheus-node-exporter.oxn-external-monitoring.svc:9100", "timestamp": 1738187977.417, "sum(rate(node_network_receive_bytes_total[1m]) + rate(node_network_transmit_bytes_total[1m])) by (instance)": 226250067.6689191, "network_bytes": 226250067.6689191, "kubernetes_prometheus_rules": "kubernetes_prometheus_rules", "add_security_context": "add_security_context", "delay_treatment": "delay_treatment"}, {"instance": "kube-prometheus-prometheus-node-exporter.oxn-external-monitoring.svc:9100", "timestamp": 1738187978.417, "sum(rate(node_network_receive_bytes_total[1m]) + rate(node_network_transmit_bytes_total[1m])) by (instance)": 1814638.8212000001, "network_bytes": 1814638.8212000001, "kubernetes_prometheus_rules": "kubernetes_prometheus_rules", "add_security_context": "add_security_context", "delay_treatment": "delay_treatment"}, {"instance": "kube-prometheus-prometheus-node-exporter.oxn-external-monitoring.svc:9100", "timestamp": 1738187979.417, "sum(rate(node_network_receive_bytes_total[1m]) + rate(node_network_transmit_bytes_total[1m])) by (instance)": 1854084.1920333337, "network_bytes": 1854084.1920333337, "kubernetes_prometheus_rules": "kubernetes_prometheus_rules", "add_security_context": "add_security_context", "delay_treatment": "delay_treatment"}, {"instance": "kube-prometheus-prometheus-node-exporter.oxn-external-monitoring.svc:9100", "timestamp": 1738187980.417, "sum(rate(node_network_receive_bytes_total[1m]) + rate(node_network_transmit_bytes_total[1m])) by (instance)": 1929386.8686651853, "network_bytes": 1929386.8686651853, "kubernetes_prometheus_rules": "kubernetes_prometheus_rules", "add_security_context": "add_security_context", "delay_treatment": "delay_treatment"}, {"instance": "kube-prometheus-prometheus-node-exporter.oxn-external-monitoring.svc:9100", "timestamp": 1738187981.417, "sum(rate(node_network_receive_bytes_total[1m]) + rate(node_network_transmit_bytes_total[1m])) by (instance)": 1969574.947554074, "network_bytes": 1969574.947554074, "kubernetes_prometheus_rules": "kubernetes_prometheus_rules", "add_security_context": "add_security_context", "delay_treatment": "delay_treatment"}, {"instance": "kube-prometheus-prometheus-node-exporter.oxn-external-monitoring.svc:9100", "timestamp": 1738187982.417, "sum(rate(node_network_receive_bytes_total[1m]) + rate(node_network_transmit_bytes_total[1m])) by (instance)": 2009763.026442963, "network_bytes": 2009763.026442963, "kubernetes_prometheus_rules": "kubernetes_prometheus_rules", "add_security_context": "add_security_context", "delay_treatment": "delay_treatment"}, {"instance": "kube-prometheus-prometheus-node-exporter.oxn-external-monitoring.svc:9100", "timestamp": 1738187983.417, "sum(rate(node_network_receive_bytes_total[1m]) + rate(node_network_transmit_bytes_total[1m])) by (instance)": 2049951.1053318519, "network_bytes": 2049951.1053318519, "kubernetes_prometheus_rules": "kubernetes_prometheus_rules", "add_security_context": "add_security_context", "delay_treatment": "delay_treatment"}, {"instance": "kube-prometheus-prometheus-node-exporter.oxn-external-monitoring.svc:9100", "timestamp": 1738187984.417, "sum(rate(node_network_receive_bytes_total[1m]) + rate(node_network_transmit_bytes_total[1m])) by (instance)": 2090139.1842207406, "network_bytes": 2090139.1842207406, "kubernetes_prometheus_rules": "kubernetes_prometheus_rules", "add_security_context": "add_security_context", "delay_treatment": "delay_treatment"}, {"instance": "kube-prometheus-prometheus-node-exporter.oxn-external-monitoring.svc:9100", "timestamp": 1738187985.417, "sum(rate(node_network_receive_bytes_total[1m]) + rate(node_network_transmit_bytes_total[1m])) by (instance)": 2240839.8022080003, "network_bytes": 2240839.8022080003, "kubernetes_prometheus_rules": "kubernetes_prometheus_rules", "add_security_context": "add_security_context", "delay_treatment": "delay_treatment"}, {"instance": "kube-prometheus-prometheus-node-exporter.oxn-external-monitoring.svc:9100", "timestamp": 1738187986.417, "sum(rate(node_network_receive_bytes_total[1m]) + rate(node_network_transmit_bytes_total[1m])) by (instance)": 2283101.3012080006, "network_bytes": 2283101.3012080006, "kubernetes_prometheus_rules": "kubernetes_prometheus_rules", "add_security_context": "add_security_context", "delay_treatment": "delay_treatment"}, {"instance": "kube-prometheus-prometheus-node-exporter.oxn-external-monitoring.svc:9100", "timestamp": 1738187987.417, "sum(rate(node_network_receive_bytes_total[1m]) + rate(node_network_transmit_bytes_total[1m])) by (instance)": 2325362.8002079995, "network_bytes": 2325362.8002079995, "kubernetes_prometheus_rules": "kubernetes_prometheus_rules", "add_security_context": "add_security_context", "delay_treatment": "delay_treatment"}, {"instance": "kube-prometheus-prometheus-node-exporter.oxn-external-monitoring.svc:9100", "timestamp": 1738187988.417, "sum(rate(node_network_receive_bytes_total[1m]) + rate(node_network_transmit_bytes_total[1m])) by (instance)": 2367624.299208, "network_bytes": 2367624.299208, "kubernetes_prometheus_rules": "kubernetes_prometheus_rules", "add_security_context": "add_security_context", "delay_treatment": "delay_treatment"}, {"instance": "kube-prometheus-prometheus-node-exporter.oxn-external-monitoring.svc:9100", "timestamp": 1738187989.417, "sum(rate(node_network_receive_bytes_total[1m]) + rate(node_network_transmit_bytes_total[1m])) by (instance)": 2489496.2989253337, "network_bytes": 2489496.2989253337, "kubernetes_prometheus_rules": "kubernetes_prometheus_rules", "add_security_context": "add_security_context", "delay_treatment": "delay_treatment"}, {"instance": "kube-prometheus-prometheus-node-exporter.oxn-external-monitoring.svc:9100", "timestamp": 1738187990.417, "sum(rate(node_network_receive_bytes_total[1m]) + rate(node_network_transmit_bytes_total[1m])) by (instance)": 2562790.303847273, "network_bytes": 2562790.303847273, "kubernetes_prometheus_rules": "kubernetes_prometheus_rules", "add_security_context": "add_security_context", "delay_treatment": "delay_treatment"}, {"instance": "kube-prometheus-prometheus-node-exporter.oxn-external-monitoring.svc:9100", "timestamp": 1738187991.417, "sum(rate(node_network_receive_bytes_total[1m]) + rate(node_network_transmit_bytes_total[1m])) by (instance)": 2575658.3986957576, "network_bytes": 2575658.3986957576, "kubernetes_prometheus_rules": "kubernetes_prometheus_rules", "add_security_context": "add_security_context", "delay_treatment": "delay_treatment"}, {"instance": "kube-prometheus-prometheus-node-exporter.oxn-external-monitoring.svc:9100", "timestamp": 1738187992.417, "sum(rate(node_network_receive_bytes_total[1m]) + rate(node_network_transmit_bytes_total[1m])) by (instance)": 2588502.31318303, "network_bytes": 2588502.31318303, "kubernetes_prometheus_rules": "kubernetes_prometheus_rules", "add_security_context": "add_security_context", "delay_treatment": "delay_treatment"}, {"instance": "kube-prometheus-prometheus-node-exporter.oxn-external-monitoring.svc:9100", "timestamp": 1738187993.417, "sum(rate(node_network_receive_bytes_total[1m]) + rate(node_network_transmit_bytes_total[1m])) by (instance)": 2596141.1636363636, "network_bytes": 2596141.1636363636, "kubernetes_prometheus_rules": "kubernetes_prometheus_rules", "add_security_context": "add_security_context", "delay_treatment": "delay_treatment"}, {"instance": "kube-prometheus-prometheus-node-exporter.oxn-external-monitoring.svc:9100", "timestamp": 1738187994.417, "sum(rate(node_network_receive_bytes_total[1m]) + rate(node_network_transmit_bytes_total[1m])) by (instance)": 2596141.1636363636, "network_bytes": 2596141.1636363636, "kubernetes_prometheus_rules": "kubernetes_prometheus_rules", "add_security_context": "add_security_context", "delay_treatment": "delay_treatment"}, {"instance": "kube-prometheus-prometheus-node-exporter.oxn-external-monitoring.svc:9100", "timestamp": 1738187995.417, "sum(rate(node_network_receive_bytes_total[1m]) + rate(node_network_transmit_bytes_total[1m])) by (instance)": 2684149.127272727, "network_bytes": 2684149.127272727, "kubernetes_prometheus_rules": "kubernetes_prometheus_rules", "add_security_context": "add_security_context", "delay_treatment": "delay_treatment"}, {"instance": "kube-prometheus-prometheus-node-exporter.oxn-external-monitoring.svc:9100", "timestamp": 1738187996.417, "sum(rate(node_network_receive_bytes_total[1m]) + rate(node_network_transmit_bytes_total[1m])) by (instance)": 2684149.127272727, "network_bytes": 2684149.127272727, "kubernetes_prometheus_rules": "kubernetes_prometheus_rules", "add_security_context": "add_security_context", "delay_treatment": "delay_treatment"}, {"instance": "kube-prometheus-prometheus-node-exporter.oxn-external-monitoring.svc:9100", "timestamp": 1738187997.417, "sum(rate(node_network_receive_bytes_total[1m]) + rate(node_network_transmit_bytes_total[1m])) by (instance)": 2684149.127272727, "network_bytes": 2684149.127272727, "kubernetes_prometheus_rules": "kubernetes_prometheus_rules", "add_security_context": "add_security_context", "delay_treatment": "delay_treatment"}, {"instance": "kube-prometheus-prometheus-node-exporter.oxn-external-monitoring.svc:9100", "timestamp": 1738187998.417, "sum(rate(node_network_receive_bytes_total[1m]) + rate(node_network_transmit_bytes_total[1m])) by (instance)": 2684149.127272727, "network_bytes": 2684149.127272727, "kubernetes_prometheus_rules": "kubernetes_prometheus_rules", "add_security_context": "add_security_context", "delay_treatment": "delay_treatment"}, {"instance": "kube-prometheus-prometheus-node-exporter.oxn-external-monitoring.svc:9100", "timestamp": 1738187999.417, "sum(rate(node_network_receive_bytes_total[1m]) + rate(node_network_transmit_bytes_total[1m])) by (instance)": 2684149.127272727, "network_bytes": 2684149.127272727, "kubernetes_prometheus_rules": "kubernetes_prometheus_rules", "add_security_context": "add_security_context", "delay_treatment": "delay_treatment"}, {"instance": "kube-prometheus-prometheus-node-exporter.oxn-external-monitoring.svc:9100", "timestamp": 1738188000.417, "sum(rate(node_network_receive_bytes_total[1m]) + rate(node_network_transmit_bytes_total[1m])) by (instance)": 2786153.909090909, "network_bytes": 2786153.909090909, "kubernetes_prometheus_rules": "kubernetes_prometheus_rules", "add_security_context": "add_security_context", "delay_treatment": "delay_treatment"}, {"instance": "kube-prometheus-prometheus-node-exporter.oxn-external-monitoring.svc:9100", "timestamp": 1738188001.417, "sum(rate(node_network_receive_bytes_total[1m]) + rate(node_network_transmit_bytes_total[1m])) by (instance)": 2786153.909090909, "network_bytes": 2786153.909090909, "kubernetes_prometheus_rules": "kubernetes_prometheus_rules", "add_security_context": "add_security_context", "delay_treatment": "delay_treatment"}, {"instance": "kube-prometheus-prometheus-node-exporter.oxn-external-monitoring.svc:9100", "timestamp": 1738188002.417, "sum(rate(node_network_receive_bytes_total[1m]) + rate(node_network_transmit_bytes_total[1m])) by (instance)": 2786153.909090909, "network_bytes": 2786153.909090909, "kubernetes_prometheus_rules": "kubernetes_prometheus_rules", "add_security_context": "add_security_context", "delay_treatment": "delay_treatment"}, {"instance": "kube-prometheus-prometheus-node-exporter.oxn-external-monitoring.svc:9100", "timestamp": 1738188003.417, "sum(rate(node_network_receive_bytes_total[1m]) + rate(node_network_transmit_bytes_total[1m])) by (instance)": 2786153.909090909, "network_bytes": 2786153.909090909, "kubernetes_prometheus_rules": "kubernetes_prometheus_rules", "add_security_context": "add_security_context", "delay_treatment": "delay_treatment"}, {"instance": "kube-prometheus-prometheus-node-exporter.oxn-external-monitoring.svc:9100", "timestamp": 1738188004.417, "sum(rate(node_network_receive_bytes_total[1m]) + rate(node_network_transmit_bytes_total[1m])) by (instance)": 2786153.909090909, "network_bytes": 2786153.909090909, "kubernetes_prometheus_rules": "kubernetes_prometheus_rules", "add_security_context": "add_security_context", "delay_treatment": "delay_treatment"}, {"instance": "kube-prometheus-prometheus-node-exporter.oxn-external-monitoring.svc:9100", "timestamp": 1738188005.417, "sum(rate(node_network_receive_bytes_total[1m]) + rate(node_network_transmit_bytes_total[1m])) by (instance)": 2869005.5818181816, "network_bytes": 2869005.5818181816, "kubernetes_prometheus_rules": "kubernetes_prometheus_rules", "add_security_context": "add_security_context", "delay_treatment": "delay_treatment"}, {"instance": "kube-prometheus-prometheus-node-exporter.oxn-external-monitoring.svc:9100", "timestamp": 1738188006.417, "sum(rate(node_network_receive_bytes_total[1m]) + rate(node_network_transmit_bytes_total[1m])) by (instance)": 2869005.5818181816, "network_bytes": 2869005.5818181816, "kubernetes_prometheus_rules": "kubernetes_prometheus_rules", "add_security_context": "add_security_context", "delay_treatment": "delay_treatment"}, {"instance": "kube-prometheus-prometheus-node-exporter.oxn-external-monitoring.svc:9100", "timestamp": 1738188007.417, "sum(rate(node_network_receive_bytes_total[1m]) + rate(node_network_transmit_bytes_total[1m])) by (instance)": 2869005.5818181816, "network_bytes": 2869005.5818181816, "kubernetes_prometheus_rules": "kubernetes_prometheus_rules", "add_security_context": "add_security_context", "delay_treatment": "delay_treatment"}, {"instance": "kube-prometheus-prometheus-node-exporter.oxn-external-monitoring.svc:9100", "timestamp": 1738188008.417, "sum(rate(node_network_receive_bytes_total[1m]) + rate(node_network_transmit_bytes_total[1m])) by (instance)": 2869005.5818181816, "network_bytes": 2869005.5818181816, "kubernetes_prometheus_rules": "kubernetes_prometheus_rules", "add_security_context": "add_security_context", "delay_treatment": "delay_treatment"}, {"instance": "kube-prometheus-prometheus-node-exporter.oxn-external-monitoring.svc:9100", "timestamp": 1738188009.417, "sum(rate(node_network_receive_bytes_total[1m]) + rate(node_network_transmit_bytes_total[1m])) by (instance)": 2869005.5818181816, "network_bytes": 2869005.5818181816, "kubernetes_prometheus_rules": "kubernetes_prometheus_rules", "add_security_context": "add_security_context", "delay_treatment": "delay_treatment"}, {"instance": "kube-prometheus-prometheus-node-exporter.oxn-external-monitoring.svc:9100", "timestamp": 1738188010.417, "sum(rate(node_network_receive_bytes_total[1m]) + rate(node_network_transmit_bytes_total[1m])) by (instance)": 2942334.5999999996, "network_bytes": 2942334.5999999996, "kubernetes_prometheus_rules": "kubernetes_prometheus_rules", "add_security_context": "add_security_context", "delay_treatment": "delay_treatment"}, {"instance": "kube-prometheus-prometheus-node-exporter.oxn-external-monitoring.svc:9100", "timestamp": 1738188011.417, "sum(rate(node_network_receive_bytes_total[1m]) + rate(node_network_transmit_bytes_total[1m])) by (instance)": 2942334.5999999996, "network_bytes": 2942334.5999999996, "kubernetes_prometheus_rules": "kubernetes_prometheus_rules", "add_security_context": "add_security_context", "delay_treatment": "delay_treatment"}, {"instance": "kube-prometheus-prometheus-node-exporter.oxn-external-monitoring.svc:9100", "timestamp": 1738188012.417, "sum(rate(node_network_receive_bytes_total[1m]) + rate(node_network_transmit_bytes_total[1m])) by (instance)": 2942334.5999999996, "network_bytes": 2942334.5999999996, "kubernetes_prometheus_rules": "kubernetes_prometheus_rules", "add_security_context": "add_security_context", "delay_treatment": "delay_treatment"}, {"instance": "kube-prometheus-prometheus-node-exporter.oxn-external-monitoring.svc:9100", "timestamp": 1738188013.417, "sum(rate(node_network_receive_bytes_total[1m]) + rate(node_network_transmit_bytes_total[1m])) by (instance)": 2942334.5999999996, "network_bytes": 2942334.5999999996, "kubernetes_prometheus_rules": "kubernetes_prometheus_rules", "add_security_context": "add_security_context", "delay_treatment": "delay_treatment"}, {"instance": "kube-prometheus-prometheus-node-exporter.oxn-external-monitoring.svc:9100", "timestamp": 1738188014.417, "sum(rate(node_network_receive_bytes_total[1m]) + rate(node_network_transmit_bytes_total[1m])) by (instance)": 2942334.5999999996, "network_bytes": 2942334.5999999996, "kubernetes_prometheus_rules": "kubernetes_prometheus_rules", "add_security_context": "add_security_context", "delay_treatment": "delay_treatment"}, {"instance": "kube-prometheus-prometheus-node-exporter.oxn-external-monitoring.svc:9100", "timestamp": 1738188015.417, "sum(rate(node_network_receive_bytes_total[1m]) + rate(node_network_transmit_bytes_total[1m])) by (instance)": 3089939.1636363636, "network_bytes": 3089939.1636363636, "kubernetes_prometheus_rules": "kubernetes_prometheus_rules", "add_security_context": "add_security_context", "delay_treatment": "delay_treatment"}, {"instance": "kube-prometheus-prometheus-node-exporter.oxn-external-monitoring.svc:9100", "timestamp": 1738188016.417, "sum(rate(node_network_receive_bytes_total[1m]) + rate(node_network_transmit_bytes_total[1m])) by (instance)": 3089939.1636363636, "network_bytes": 3089939.1636363636, "kubernetes_prometheus_rules": "kubernetes_prometheus_rules", "add_security_context": "add_security_context", "delay_treatment": "delay_treatment"}, {"instance": "kube-prometheus-prometheus-node-exporter.oxn-external-monitoring.svc:9100", "timestamp": 1738188017.417, "sum(rate(node_network_receive_bytes_total[1m]) + rate(node_network_transmit_bytes_total[1m])) by (instance)": 3089939.1636363636, "network_bytes": 3089939.1636363636, "kubernetes_prometheus_rules": "kubernetes_prometheus_rules", "add_security_context": "add_security_context", "delay_treatment": "delay_treatment"}, {"instance": "kube-prometheus-prometheus-node-exporter.oxn-external-monitoring.svc:9100", "timestamp": 1738188018.417, "sum(rate(node_network_receive_bytes_total[1m]) + rate(node_network_transmit_bytes_total[1m])) by (instance)": 3089939.1636363636, "network_bytes": 3089939.1636363636, "kubernetes_prometheus_rules": "kubernetes_prometheus_rules", "add_security_context": "add_security_context", "delay_treatment": "delay_treatment"}, {"instance": "kube-prometheus-prometheus-node-exporter.oxn-external-monitoring.svc:9100", "timestamp": 1738188019.417, "sum(rate(node_network_receive_bytes_total[1m]) + rate(node_network_transmit_bytes_total[1m])) by (instance)": 3089939.1636363636, "network_bytes": 3089939.1636363636, "kubernetes_prometheus_rules": "kubernetes_prometheus_rules", "add_security_context": "add_security_context", "delay_treatment": "delay_treatment"}, {"instance": "kube-prometheus-prometheus-node-exporter.oxn-external-monitoring.svc:9100", "timestamp": 1738188020.417, "sum(rate(node_network_receive_bytes_total[1m]) + rate(node_network_transmit_bytes_total[1m])) by (instance)": 3207779.6545454543, "network_bytes": 3207779.6545454543, "kubernetes_prometheus_rules": "kubernetes_prometheus_rules", "add_security_context": "add_security_context", "delay_treatment": "delay_treatment"}, {"instance": "kube-prometheus-prometheus-node-exporter.oxn-external-monitoring.svc:9100", "timestamp": 1738188021.417, "sum(rate(node_network_receive_bytes_total[1m]) + rate(node_network_transmit_bytes_total[1m])) by (instance)": 3207779.6545454543, "network_bytes": 3207779.6545454543, "kubernetes_prometheus_rules": "kubernetes_prometheus_rules", "add_security_context": "add_security_context", "delay_treatment": "delay_treatment"}, {"instance": "kube-prometheus-prometheus-node-exporter.oxn-external-monitoring.svc:9100", "timestamp": 1738188022.417, "sum(rate(node_network_receive_bytes_total[1m]) + rate(node_network_transmit_bytes_total[1m])) by (instance)": 3207779.6545454543, "network_bytes": 3207779.6545454543, "kubernetes_prometheus_rules": "kubernetes_prometheus_rules", "add_security_context": "add_security_context", "delay_treatment": "delay_treatment"}, {"instance": "kube-prometheus-prometheus-node-exporter.oxn-external-monitoring.svc:9100", "timestamp": 1738188023.417, "sum(rate(node_network_receive_bytes_total[1m]) + rate(node_network_transmit_bytes_total[1m])) by (instance)": 3207779.6545454543, "network_bytes": 3207779.6545454543, "kubernetes_prometheus_rules": "kubernetes_prometheus_rules", "add_security_context": "add_security_context", "delay_treatment": "delay_treatment"}, {"instance": "kube-prometheus-prometheus-node-exporter.oxn-external-monitoring.svc:9100", "timestamp": 1738188024.417, "sum(rate(node_network_receive_bytes_total[1m]) + rate(node_network_transmit_bytes_total[1m])) by (instance)": 3207779.6545454543, "network_bytes": 3207779.6545454543, "kubernetes_prometheus_rules": "kubernetes_prometheus_rules", "add_security_context": "add_security_context", "delay_treatment": "delay_treatment"}, {"instance": "kube-prometheus-prometheus-node-exporter.oxn-external-monitoring.svc:9100", "timestamp": 1738188025.417, "sum(rate(node_network_receive_bytes_total[1m]) + rate(node_network_transmit_bytes_total[1m])) by (instance)": 3288756.090909091, "network_bytes": 3288756.090909091, "kubernetes_prometheus_rules": "kubernetes_prometheus_rules", "add_security_context": "add_security_context", "delay_treatment": "delay_treatment"}, {"instance": "kube-prometheus-prometheus-node-exporter.oxn-external-monitoring.svc:9100", "timestamp": 1738188026.417, "sum(rate(node_network_receive_bytes_total[1m]) + rate(node_network_transmit_bytes_total[1m])) by (instance)": 3288756.090909091, "network_bytes": 3288756.090909091, "kubernetes_prometheus_rules": "kubernetes_prometheus_rules", "add_security_context": "add_security_context", "delay_treatment": "delay_treatment"}, {"instance": "kube-prometheus-prometheus-node-exporter.oxn-external-monitoring.svc:9100", "timestamp": 1738188027.417, "sum(rate(node_network_receive_bytes_total[1m]) + rate(node_network_transmit_bytes_total[1m])) by (instance)": 3288756.090909091, "network_bytes": 3288756.090909091, "kubernetes_prometheus_rules": "kubernetes_prometheus_rules", "add_security_context": "add_security_context", "delay_treatment": "delay_treatment"}, {"instance": "kube-prometheus-prometheus-node-exporter.oxn-external-monitoring.svc:9100", "timestamp": 1738188028.417, "sum(rate(node_network_receive_bytes_total[1m]) + rate(node_network_transmit_bytes_total[1m])) by (instance)": 3288756.090909091, "network_bytes": 3288756.090909091, "kubernetes_prometheus_rules": "kubernetes_prometheus_rules", "add_security_context": "add_security_context", "delay_treatment": "delay_treatment"}, {"instance": "kube-prometheus-prometheus-node-exporter.oxn-external-monitoring.svc:9100", "timestamp": 1738188029.417, "sum(rate(node_network_receive_bytes_total[1m]) + rate(node_network_transmit_bytes_total[1m])) by (instance)": 3288756.090909091, "network_bytes": 3288756.090909091, "kubernetes_prometheus_rules": "kubernetes_prometheus_rules", "add_security_context": "add_security_context", "delay_treatment": "delay_treatment"}, {"instance": "kube-prometheus-prometheus-node-exporter.oxn-external-monitoring.svc:9100", "timestamp": 1738188030.417, "sum(rate(node_network_receive_bytes_total[1m]) + rate(node_network_transmit_bytes_total[1m])) by (instance)": 3361985.2727272725, "network_bytes": 3361985.2727272725, "kubernetes_prometheus_rules": "kubernetes_prometheus_rules", "add_security_context": "add_security_context", "delay_treatment": "delay_treatment"}, {"instance": "kube-prometheus-prometheus-node-exporter.oxn-external-monitoring.svc:9100", "timestamp": 1738188031.417, "sum(rate(node_network_receive_bytes_total[1m]) + rate(node_network_transmit_bytes_total[1m])) by (instance)": 3361985.2727272725, "network_bytes": 3361985.2727272725, "kubernetes_prometheus_rules": "kubernetes_prometheus_rules", "add_security_context": "add_security_context", "delay_treatment": "delay_treatment"}, {"instance": "kube-prometheus-prometheus-node-exporter.oxn-external-monitoring.svc:9100", "timestamp": 1738188032.417, "sum(rate(node_network_receive_bytes_total[1m]) + rate(node_network_transmit_bytes_total[1m])) by (instance)": 3361985.2727272725, "network_bytes": 3361985.2727272725, "kubernetes_prometheus_rules": "kubernetes_prometheus_rules", "add_security_context": "add_security_context", "delay_treatment": "delay_treatment"}, {"instance": "kube-prometheus-prometheus-node-exporter.oxn-external-monitoring.svc:9100", "timestamp": 1738188033.417, "sum(rate(node_network_receive_bytes_total[1m]) + rate(node_network_transmit_bytes_total[1m])) by (instance)": 3361985.2727272725, "network_bytes": 3361985.2727272725, "kubernetes_prometheus_rules": "kubernetes_prometheus_rules", "add_security_context": "add_security_context", "delay_treatment": "delay_treatment"}, {"instance": "kube-prometheus-prometheus-node-exporter.oxn-external-monitoring.svc:9100", "timestamp": 1738188034.417, "sum(rate(node_network_receive_bytes_total[1m]) + rate(node_network_transmit_bytes_total[1m])) by (instance)": 3361985.2727272725, "network_bytes": 3361985.2727272725, "kubernetes_prometheus_rules": "kubernetes_prometheus_rules", "add_security_context": "add_security_context", "delay_treatment": "delay_treatment"}, {"instance": "kube-prometheus-prometheus-node-exporter.oxn-external-monitoring.svc:9100", "timestamp": 1738188035.417, "sum(rate(node_network_receive_bytes_total[1m]) + rate(node_network_transmit_bytes_total[1m])) by (instance)": 3369733.290909091, "network_bytes": 3369733.290909091, "kubernetes_prometheus_rules": "kubernetes_prometheus_rules", "add_security_context": "add_security_context", "delay_treatment": "delay_treatment"}, {"instance": "kube-prometheus-prometheus-node-exporter.oxn-external-monitoring.svc:9100", "timestamp": 1738188036.417, "sum(rate(node_network_receive_bytes_total[1m]) + rate(node_network_transmit_bytes_total[1m])) by (instance)": 3369733.290909091, "network_bytes": 3369733.290909091, "kubernetes_prometheus_rules": "kubernetes_prometheus_rules", "add_security_context": "add_security_context", "delay_treatment": "delay_treatment"}, {"instance": "kube-prometheus-prometheus-node-exporter.oxn-external-monitoring.svc:9100", "timestamp": 1738188037.417, "sum(rate(node_network_receive_bytes_total[1m]) + rate(node_network_transmit_bytes_total[1m])) by (instance)": 3369733.290909091, "network_bytes": 3369733.290909091, "kubernetes_prometheus_rules": "kubernetes_prometheus_rules", "add_security_context": "add_security_context", "delay_treatment": "delay_treatment"}, {"instance": "kube-prometheus-prometheus-node-exporter.oxn-external-monitoring.svc:9100", "timestamp": 1738188038.417, "sum(rate(node_network_receive_bytes_total[1m]) + rate(node_network_transmit_bytes_total[1m])) by (instance)": 3369733.290909091, "network_bytes": 3369733.290909091, "kubernetes_prometheus_rules": "kubernetes_prometheus_rules", "add_security_context": "add_security_context", "delay_treatment": "delay_treatment"}, {"instance": "kube-prometheus-prometheus-node-exporter.oxn-external-monitoring.svc:9100", "timestamp": 1738188039.417, "sum(rate(node_network_receive_bytes_total[1m]) + rate(node_network_transmit_bytes_total[1m])) by (instance)": 3369733.290909091, "network_bytes": 3369733.290909091, "kubernetes_prometheus_rules": "kubernetes_prometheus_rules", "add_security_context": "add_security_context", "delay_treatment": "delay_treatment"}, {"instance": "kube-prometheus-prometheus-node-exporter.oxn-external-monitoring.svc:9100", "timestamp": 1738188040.417, "sum(rate(node_network_receive_bytes_total[1m]) + rate(node_network_transmit_bytes_total[1m])) by (instance)": 3358132.818181818, "network_bytes": 3358132.818181818, "kubernetes_prometheus_rules": "kubernetes_prometheus_rules", "add_security_context": "add_security_context", "delay_treatment": "delay_treatment"}, {"instance": "kube-prometheus-prometheus-node-exporter.oxn-external-monitoring.svc:9100", "timestamp": 1738188041.417, "sum(rate(node_network_receive_bytes_total[1m]) + rate(node_network_transmit_bytes_total[1m])) by (instance)": 3358132.818181818, "network_bytes": 3358132.818181818, "kubernetes_prometheus_rules": "kubernetes_prometheus_rules", "add_security_context": "add_security_context", "delay_treatment": "delay_treatment"}, {"instance": "kube-prometheus-prometheus-node-exporter.oxn-external-monitoring.svc:9100", "timestamp": 1738188042.417, "sum(rate(node_network_receive_bytes_total[1m]) + rate(node_network_transmit_bytes_total[1m])) by (instance)": 3358132.818181818, "network_bytes": 3358132.818181818, "kubernetes_prometheus_rules": "kubernetes_prometheus_rules", "add_security_context": "add_security_context", "delay_treatment": "delay_treatment"}, {"instance": "kube-prometheus-prometheus-node-exporter.oxn-external-monitoring.svc:9100", "timestamp": 1738188043.417, "sum(rate(node_network_receive_bytes_total[1m]) + rate(node_network_transmit_bytes_total[1m])) by (instance)": 3358132.818181818, "network_bytes": 3358132.818181818, "kubernetes_prometheus_rules": "kubernetes_prometheus_rules", "add_security_context": "add_security_context", "delay_treatment": "delay_treatment"}, {"instance": "kube-prometheus-prometheus-node-exporter.oxn-external-monitoring.svc:9100", "timestamp": 1738188044.417, "sum(rate(node_network_receive_bytes_total[1m]) + rate(node_network_transmit_bytes_total[1m])) by (instance)": 3358132.818181818, "network_bytes": 3358132.818181818, "kubernetes_prometheus_rules": "kubernetes_prometheus_rules", "add_security_context": "add_security_context", "delay_treatment": "delay_treatment"}, {"instance": "kube-prometheus-prometheus-node-exporter.oxn-external-monitoring.svc:9100", "timestamp": 1738188045.417, "sum(rate(node_network_receive_bytes_total[1m]) + rate(node_network_transmit_bytes_total[1m])) by (instance)": 3426993.5818181816, "network_bytes": 3426993.5818181816, "kubernetes_prometheus_rules": "kubernetes_prometheus_rules", "add_security_context": "add_security_context", "delay_treatment": "delay_treatment"}, {"instance": "kube-prometheus-prometheus-node-exporter.oxn-external-monitoring.svc:9100", "timestamp": 1738188046.417, "sum(rate(node_network_receive_bytes_total[1m]) + rate(node_network_transmit_bytes_total[1m])) by (instance)": 3426993.5818181816, "network_bytes": 3426993.5818181816, "kubernetes_prometheus_rules": "kubernetes_prometheus_rules", "add_security_context": "add_security_context", "delay_treatment": "delay_treatment"}, {"instance": "kube-prometheus-prometheus-node-exporter.oxn-external-monitoring.svc:9100", "timestamp": 1738188047.417, "sum(rate(node_network_receive_bytes_total[1m]) + rate(node_network_transmit_bytes_total[1m])) by (instance)": 3426993.5818181816, "network_bytes": 3426993.5818181816, "kubernetes_prometheus_rules": "kubernetes_prometheus_rules", "add_security_context": "add_security_context", "delay_treatment": "delay_treatment"}, {"instance": "kube-prometheus-prometheus-node-exporter.oxn-external-monitoring.svc:9100", "timestamp": 1738188048.417, "sum(rate(node_network_receive_bytes_total[1m]) + rate(node_network_transmit_bytes_total[1m])) by (instance)": 3426993.5818181816, "network_bytes": 3426993.5818181816, "kubernetes_prometheus_rules": "kubernetes_prometheus_rules", "add_security_context": "add_security_context", "delay_treatment": "delay_treatment"}, {"instance": "kube-prometheus-prometheus-node-exporter.oxn-external-monitoring.svc:9100", "timestamp": 1738188049.417, "sum(rate(node_network_receive_bytes_total[1m]) + rate(node_network_transmit_bytes_total[1m])) by (instance)": 3426993.5818181816, "network_bytes": 3426993.5818181816, "kubernetes_prometheus_rules": "kubernetes_prometheus_rules", "add_security_context": "add_security_context", "delay_treatment": "delay_treatment"}, {"instance": "kube-prometheus-prometheus-node-exporter.oxn-external-monitoring.svc:9100", "timestamp": 1738188050.417, "sum(rate(node_network_receive_bytes_total[1m]) + rate(node_network_transmit_bytes_total[1m])) by (instance)": 3460830.290909091, "network_bytes": 3460830.290909091, "kubernetes_prometheus_rules": "kubernetes_prometheus_rules", "add_security_context": "add_security_context", "delay_treatment": "delay_treatment"}, {"instance": "kube-prometheus-prometheus-node-exporter.oxn-external-monitoring.svc:9100", "timestamp": 1738188051.417, "sum(rate(node_network_receive_bytes_total[1m]) + rate(node_network_transmit_bytes_total[1m])) by (instance)": 3460830.290909091, "network_bytes": 3460830.290909091, "kubernetes_prometheus_rules": "kubernetes_prometheus_rules", "add_security_context": "add_security_context", "delay_treatment": "delay_treatment"}, {"instance": "kube-prometheus-prometheus-node-exporter.oxn-external-monitoring.svc:9100", "timestamp": 1738188052.417, "sum(rate(node_network_receive_bytes_total[1m]) + rate(node_network_transmit_bytes_total[1m])) by (instance)": 3460830.290909091, "network_bytes": 3460830.290909091, "kubernetes_prometheus_rules": "kubernetes_prometheus_rules", "add_security_context": "add_security_context", "delay_treatment": "delay_treatment"}, {"instance": "kube-prometheus-prometheus-node-exporter.oxn-external-monitoring.svc:9100", "timestamp": 1738188053.417, "sum(rate(node_network_receive_bytes_total[1m]) + rate(node_network_transmit_bytes_total[1m])) by (instance)": 3460830.290909091, "network_bytes": 3460830.290909091, "kubernetes_prometheus_rules": "kubernetes_prometheus_rules", "add_security_context": "add_security_context", "delay_treatment": "delay_treatment"}, {"instance": "kube-prometheus-prometheus-node-exporter.oxn-external-monitoring.svc:9100", "timestamp": 1738188054.417, "sum(rate(node_network_receive_bytes_total[1m]) + rate(node_network_transmit_bytes_total[1m])) by (instance)": 3460830.290909091, "network_bytes": 3460830.290909091, "kubernetes_prometheus_rules": "kubernetes_prometheus_rules", "add_security_context": "add_security_context", "delay_treatment": "delay_treatment"}, {"instance": "kube-prometheus-prometheus-node-exporter.oxn-external-monitoring.svc:9100", "timestamp": 1738188055.417, "sum(rate(node_network_receive_bytes_total[1m]) + rate(node_network_transmit_bytes_total[1m])) by (instance)": 3482356.3636363633, "network_bytes": 3482356.3636363633, "kubernetes_prometheus_rules": "kubernetes_prometheus_rules", "add_security_context": "add_security_context", "delay_treatment": "delay_treatment"}, {"instance": "kube-prometheus-prometheus-node-exporter.oxn-external-monitoring.svc:9100", "timestamp": 1738188056.417, "sum(rate(node_network_receive_bytes_total[1m]) + rate(node_network_transmit_bytes_total[1m])) by (instance)": 3482356.3636363633, "network_bytes": 3482356.3636363633, "kubernetes_prometheus_rules": "kubernetes_prometheus_rules", "add_security_context": "add_security_context", "delay_treatment": "delay_treatment"}, {"instance": "kube-prometheus-prometheus-node-exporter.oxn-external-monitoring.svc:9100", "timestamp": 1738188057.417, "sum(rate(node_network_receive_bytes_total[1m]) + rate(node_network_transmit_bytes_total[1m])) by (instance)": 3482356.3636363633, "network_bytes": 3482356.3636363633, "kubernetes_prometheus_rules": "kubernetes_prometheus_rules", "add_security_context": "add_security_context", "delay_treatment": "delay_treatment"}, {"instance": "kube-prometheus-prometheus-node-exporter.oxn-external-monitoring.svc:9100", "timestamp": 1738188058.417, "sum(rate(node_network_receive_bytes_total[1m]) + rate(node_network_transmit_bytes_total[1m])) by (instance)": 3482356.3636363633, "network_bytes": 3482356.3636363633, "kubernetes_prometheus_rules": "kubernetes_prometheus_rules", "add_security_context": "add_security_context", "delay_treatment": "delay_treatment"}, {"instance": "kube-prometheus-prometheus-node-exporter.oxn-external-monitoring.svc:9100", "timestamp": 1738188059.417, "sum(rate(node_network_receive_bytes_total[1m]) + rate(node_network_transmit_bytes_total[1m])) by (instance)": 3482356.3636363633, "network_bytes": 3482356.3636363633, "kubernetes_prometheus_rules": "kubernetes_prometheus_rules", "add_security_context": "add_security_context", "delay_treatment": "delay_treatment"}, {"instance": "kube-prometheus-prometheus-node-exporter.oxn-external-monitoring.svc:9100", "timestamp": 1738188060.417, "sum(rate(node_network_receive_bytes_total[1m]) + rate(node_network_transmit_bytes_total[1m])) by (instance)": 3505553.7818181817, "network_bytes": 3505553.7818181817, "kubernetes_prometheus_rules": "kubernetes_prometheus_rules", "add_security_context": "add_security_context", "delay_treatment": "delay_treatment"}, {"instance": "kube-prometheus-prometheus-node-exporter.oxn-external-monitoring.svc:9100", "timestamp": 1738188061.417, "sum(rate(node_network_receive_bytes_total[1m]) + rate(node_network_transmit_bytes_total[1m])) by (instance)": 3505553.7818181817, "network_bytes": 3505553.7818181817, "kubernetes_prometheus_rules": "kubernetes_prometheus_rules", "add_security_context": "add_security_context", "delay_treatment": "delay_treatment"}, {"instance": "kube-prometheus-prometheus-node-exporter.oxn-external-monitoring.svc:9100", "timestamp": 1738188062.417, "sum(rate(node_network_receive_bytes_total[1m]) + rate(node_network_transmit_bytes_total[1m])) by (instance)": 3505553.7818181817, "network_bytes": 3505553.7818181817, "kubernetes_prometheus_rules": "kubernetes_prometheus_rules", "add_security_context": "add_security_context", "delay_treatment": "delay_treatment"}, {"instance": "kube-prometheus-prometheus-node-exporter.oxn-external-monitoring.svc:9100", "timestamp": 1738188063.417, "sum(rate(node_network_receive_bytes_total[1m]) + rate(node_network_transmit_bytes_total[1m])) by (instance)": 3505553.7818181817, "network_bytes": 3505553.7818181817, "kubernetes_prometheus_rules": "kubernetes_prometheus_rules", "add_security_context": "add_security_context", "delay_treatment": "delay_treatment"}, {"instance": "kube-prometheus-prometheus-node-exporter.oxn-external-monitoring.svc:9100", "timestamp": 1738188064.417, "sum(rate(node_network_receive_bytes_total[1m]) + rate(node_network_transmit_bytes_total[1m])) by (instance)": 3505553.7818181817, "network_bytes": 3505553.7818181817, "kubernetes_prometheus_rules": "kubernetes_prometheus_rules", "add_security_context": "add_security_context", "delay_treatment": "delay_treatment"}, {"instance": "kube-prometheus-prometheus-node-exporter.oxn-external-monitoring.svc:9100", "timestamp": 1738188065.417, "sum(rate(node_network_receive_bytes_total[1m]) + rate(node_network_transmit_bytes_total[1m])) by (instance)": 3490469.5272727273, "network_bytes": 3490469.5272727273, "kubernetes_prometheus_rules": "kubernetes_prometheus_rules", "add_security_context": "add_security_context", "delay_treatment": "delay_treatment"}, {"instance": "kube-prometheus-prometheus-node-exporter.oxn-external-monitoring.svc:9100", "timestamp": 1738188066.417, "sum(rate(node_network_receive_bytes_total[1m]) + rate(node_network_transmit_bytes_total[1m])) by (instance)": 3490469.5272727273, "network_bytes": 3490469.5272727273, "kubernetes_prometheus_rules": "kubernetes_prometheus_rules", "add_security_context": "add_security_context", "delay_treatment": "delay_treatment"}, {"instance": "kube-prometheus-prometheus-node-exporter.oxn-external-monitoring.svc:9100", "timestamp": 1738188067.417, "sum(rate(node_network_receive_bytes_total[1m]) + rate(node_network_transmit_bytes_total[1m])) by (instance)": 3490469.5272727273, "network_bytes": 3490469.5272727273, "kubernetes_prometheus_rules": "kubernetes_prometheus_rules", "add_security_context": "add_security_context", "delay_treatment": "delay_treatment"}, {"instance": "kube-prometheus-prometheus-node-exporter.oxn-external-monitoring.svc:9100", "timestamp": 1738188068.417, "sum(rate(node_network_receive_bytes_total[1m]) + rate(node_network_transmit_bytes_total[1m])) by (instance)": 3490469.5272727273, "network_bytes": 3490469.5272727273, "kubernetes_prometheus_rules": "kubernetes_prometheus_rules", "add_security_context": "add_security_context", "delay_treatment": "delay_treatment"}, {"instance": "kube-prometheus-prometheus-node-exporter.oxn-external-monitoring.svc:9100", "timestamp": 1738188069.417, "sum(rate(node_network_receive_bytes_total[1m]) + rate(node_network_transmit_bytes_total[1m])) by (instance)": 3490469.5272727273, "network_bytes": 3490469.5272727273, "kubernetes_prometheus_rules": "kubernetes_prometheus_rules", "add_security_context": "add_security_context", "delay_treatment": "delay_treatment"}, {"instance": "kube-prometheus-prometheus-node-exporter.oxn-external-monitoring.svc:9100", "timestamp": 1738188070.417, "sum(rate(node_network_receive_bytes_total[1m]) + rate(node_network_transmit_bytes_total[1m])) by (instance)": 3477861.5636363635, "network_bytes": 3477861.5636363635, "kubernetes_prometheus_rules": "kubernetes_prometheus_rules", "add_security_context": "add_security_context", "delay_treatment": "delay_treatment"}, {"instance": "kube-prometheus-prometheus-node-exporter.oxn-external-monitoring.svc:9100", "timestamp": 1738188071.417, "sum(rate(node_network_receive_bytes_total[1m]) + rate(node_network_transmit_bytes_total[1m])) by (instance)": 3477861.5636363635, "network_bytes": 3477861.5636363635, "kubernetes_prometheus_rules": "kubernetes_prometheus_rules", "add_security_context": "add_security_context", "delay_treatment": "delay_treatment"}, {"instance": "kube-prometheus-prometheus-node-exporter.oxn-external-monitoring.svc:9100", "timestamp": 1738188072.417, "sum(rate(node_network_receive_bytes_total[1m]) + rate(node_network_transmit_bytes_total[1m])) by (instance)": 3477861.5636363635, "network_bytes": 3477861.5636363635, "kubernetes_prometheus_rules": "kubernetes_prometheus_rules", "add_security_context": "add_security_context", "delay_treatment": "delay_treatment"}, {"instance": "kube-prometheus-prometheus-node-exporter.oxn-external-monitoring.svc:9100", "timestamp": 1738188073.417, "sum(rate(node_network_receive_bytes_total[1m]) + rate(node_network_transmit_bytes_total[1m])) by (instance)": 3477861.5636363635, "network_bytes": 3477861.5636363635, "kubernetes_prometheus_rules": "kubernetes_prometheus_rules", "add_security_context": "add_security_context", "delay_treatment": "delay_treatment"}, {"instance": "kube-prometheus-prometheus-node-exporter.oxn-external-monitoring.svc:9100", "timestamp": 1738188074.417, "sum(rate(node_network_receive_bytes_total[1m]) + rate(node_network_transmit_bytes_total[1m])) by (instance)": 3477861.5636363635, "network_bytes": 3477861.5636363635, "kubernetes_prometheus_rules": "kubernetes_prometheus_rules", "add_security_context": "add_security_context", "delay_treatment": "delay_treatment"}, {"instance": "kube-prometheus-prometheus-node-exporter.oxn-external-monitoring.svc:9100", "timestamp": 1738188075.417, "sum(rate(node_network_receive_bytes_total[1m]) + rate(node_network_transmit_bytes_total[1m])) by (instance)": 3528575.4727272727, "network_bytes": 3528575.4727272727, "kubernetes_prometheus_rules": "kubernetes_prometheus_rules", "add_security_context": "add_security_context", "delay_treatment": "delay_treatment"}, {"instance": "kube-prometheus-prometheus-node-exporter.oxn-external-monitoring.svc:9100", "timestamp": 1738188076.417, "sum(rate(node_network_receive_bytes_total[1m]) + rate(node_network_transmit_bytes_total[1m])) by (instance)": 3528575.4727272727, "network_bytes": 3528575.4727272727, "kubernetes_prometheus_rules": "kubernetes_prometheus_rules", "add_security_context": "add_security_context", "delay_treatment": "delay_treatment"}, {"instance": "kube-prometheus-prometheus-node-exporter.oxn-external-monitoring.svc:9100", "timestamp": 1738188077.417, "sum(rate(node_network_receive_bytes_total[1m]) + rate(node_network_transmit_bytes_total[1m])) by (instance)": 3528575.4727272727, "network_bytes": 3528575.4727272727, "kubernetes_prometheus_rules": "kubernetes_prometheus_rules", "add_security_context": "add_security_context", "delay_treatment": "delay_treatment"}, {"instance": "kube-prometheus-prometheus-node-exporter.oxn-external-monitoring.svc:9100", "timestamp": 1738188078.417, "sum(rate(node_network_receive_bytes_total[1m]) + rate(node_network_transmit_bytes_total[1m])) by (instance)": 3528575.4727272727, "network_bytes": 3528575.4727272727, "kubernetes_prometheus_rules": "kubernetes_prometheus_rules", "add_security_context": "add_security_context", "delay_treatment": "delay_treatment"}, {"instance": "kube-prometheus-prometheus-node-exporter.oxn-external-monitoring.svc:9100", "timestamp": 1738188079.417, "sum(rate(node_network_receive_bytes_total[1m]) + rate(node_network_transmit_bytes_total[1m])) by (instance)": 3528575.4727272727, "network_bytes": 3528575.4727272727, "kubernetes_prometheus_rules": "kubernetes_prometheus_rules", "add_security_context": "add_security_context", "delay_treatment": "delay_treatment"}, {"instance": "kube-prometheus-prometheus-node-exporter.oxn-external-monitoring.svc:9100", "timestamp": 1738188080.417, "sum(rate(node_network_receive_bytes_total[1m]) + rate(node_network_transmit_bytes_total[1m])) by (instance)": 3557534.690909091, "network_bytes": 3557534.690909091, "kubernetes_prometheus_rules": "kubernetes_prometheus_rules", "add_security_context": "add_security_context", "delay_treatment": "delay_treatment"}, {"instance": "kube-prometheus-prometheus-node-exporter.oxn-external-monitoring.svc:9100", "timestamp": 1738188081.417, "sum(rate(node_network_receive_bytes_total[1m]) + rate(node_network_transmit_bytes_total[1m])) by (instance)": 3557534.690909091, "network_bytes": 3557534.690909091, "kubernetes_prometheus_rules": "kubernetes_prometheus_rules", "add_security_context": "add_security_context", "delay_treatment": "delay_treatment"}, {"instance": "kube-prometheus-prometheus-node-exporter.oxn-external-monitoring.svc:9100", "timestamp": 1738188082.417, "sum(rate(node_network_receive_bytes_total[1m]) + rate(node_network_transmit_bytes_total[1m])) by (instance)": 3557534.690909091, "network_bytes": 3557534.690909091, "kubernetes_prometheus_rules": "kubernetes_prometheus_rules", "add_security_context": "add_security_context", "delay_treatment": "delay_treatment"}, {"instance": "kube-prometheus-prometheus-node-exporter.oxn-external-monitoring.svc:9100", "timestamp": 1738188083.417, "sum(rate(node_network_receive_bytes_total[1m]) + rate(node_network_transmit_bytes_total[1m])) by (instance)": 3557534.690909091, "network_bytes": 3557534.690909091, "kubernetes_prometheus_rules": "kubernetes_prometheus_rules", "add_security_context": "add_security_context", "delay_treatment": "delay_treatment"}, {"instance": "kube-prometheus-prometheus-node-exporter.oxn-external-monitoring.svc:9100", "timestamp": 1738188084.417, "sum(rate(node_network_receive_bytes_total[1m]) + rate(node_network_transmit_bytes_total[1m])) by (instance)": 3557534.690909091, "network_bytes": 3557534.690909091, "kubernetes_prometheus_rules": "kubernetes_prometheus_rules", "add_security_context": "add_security_context", "delay_treatment": "delay_treatment"}, {"instance": "kube-prometheus-prometheus-node-exporter.oxn-external-monitoring.svc:9100", "timestamp": 1738188085.417, "sum(rate(node_network_receive_bytes_total[1m]) + rate(node_network_transmit_bytes_total[1m])) by (instance)": 3553655.618181818, "network_bytes": 3553655.618181818, "kubernetes_prometheus_rules": "kubernetes_prometheus_rules", "add_security_context": "add_security_context", "delay_treatment": "delay_treatment"}, {"instance": "kube-prometheus-prometheus-node-exporter.oxn-external-monitoring.svc:9100", "timestamp": 1738188086.417, "sum(rate(node_network_receive_bytes_total[1m]) + rate(node_network_transmit_bytes_total[1m])) by (instance)": 3553655.618181818, "network_bytes": 3553655.618181818, "kubernetes_prometheus_rules": "kubernetes_prometheus_rules", "add_security_context": "add_security_context", "delay_treatment": "delay_treatment"}, {"instance": "kube-prometheus-prometheus-node-exporter.oxn-external-monitoring.svc:9100", "timestamp": 1738188087.417, "sum(rate(node_network_receive_bytes_total[1m]) + rate(node_network_transmit_bytes_total[1m])) by (instance)": 3553655.618181818, "network_bytes": 3553655.618181818, "kubernetes_prometheus_rules": "kubernetes_prometheus_rules", "add_security_context": "add_security_context", "delay_treatment": "delay_treatment"}, {"instance": "kube-prometheus-prometheus-node-exporter.oxn-external-monitoring.svc:9100", "timestamp": 1738188088.417, "sum(rate(node_network_receive_bytes_total[1m]) + rate(node_network_transmit_bytes_total[1m])) by (instance)": 3553655.618181818, "network_bytes": 3553655.618181818, "kubernetes_prometheus_rules": "kubernetes_prometheus_rules", "add_security_context": "add_security_context", "delay_treatment": "delay_treatment"}, {"instance": "kube-prometheus-prometheus-node-exporter.oxn-external-monitoring.svc:9100", "timestamp": 1738188089.417, "sum(rate(node_network_receive_bytes_total[1m]) + rate(node_network_transmit_bytes_total[1m])) by (instance)": 3553655.618181818, "network_bytes": 3553655.618181818, "kubernetes_prometheus_rules": "kubernetes_prometheus_rules", "add_security_context": "add_security_context", "delay_treatment": "delay_treatment"}, {"instance": "kube-prometheus-prometheus-node-exporter.oxn-external-monitoring.svc:9100", "timestamp": 1738188090.417, "sum(rate(node_network_receive_bytes_total[1m]) + rate(node_network_transmit_bytes_total[1m])) by (instance)": 3614638.981818182, "network_bytes": 3614638.981818182, "kubernetes_prometheus_rules": "kubernetes_prometheus_rules", "add_security_context": "add_security_context", "delay_treatment": "delay_treatment"}, {"instance": "kube-prometheus-prometheus-node-exporter.oxn-external-monitoring.svc:9100", "timestamp": 1738188091.417, "sum(rate(node_network_receive_bytes_total[1m]) + rate(node_network_transmit_bytes_total[1m])) by (instance)": 3614638.981818182, "network_bytes": 3614638.981818182, "kubernetes_prometheus_rules": "kubernetes_prometheus_rules", "add_security_context": "add_security_context", "delay_treatment": "delay_treatment"}, {"instance": "kube-prometheus-prometheus-node-exporter.oxn-external-monitoring.svc:9100", "timestamp": 1738188092.417, "sum(rate(node_network_receive_bytes_total[1m]) + rate(node_network_transmit_bytes_total[1m])) by (instance)": 3614638.981818182, "network_bytes": 3614638.981818182, "kubernetes_prometheus_rules": "kubernetes_prometheus_rules", "add_security_context": "add_security_context", "delay_treatment": "delay_treatment"}, {"instance": "kube-prometheus-prometheus-node-exporter.oxn-external-monitoring.svc:9100", "timestamp": 1738188093.417, "sum(rate(node_network_receive_bytes_total[1m]) + rate(node_network_transmit_bytes_total[1m])) by (instance)": 3614638.981818182, "network_bytes": 3614638.981818182, "kubernetes_prometheus_rules": "kubernetes_prometheus_rules", "add_security_context": "add_security_context", "delay_treatment": "delay_treatment"}, {"instance": "kube-prometheus-prometheus-node-exporter.oxn-external-monitoring.svc:9100", "timestamp": 1738188094.417, "sum(rate(node_network_receive_bytes_total[1m]) + rate(node_network_transmit_bytes_total[1m])) by (instance)": 3614638.981818182, "network_bytes": 3614638.981818182, "kubernetes_prometheus_rules": "kubernetes_prometheus_rules", "add_security_context": "add_security_context", "delay_treatment": "delay_treatment"}, {"instance": "kube-prometheus-prometheus-node-exporter.oxn-external-monitoring.svc:9100", "timestamp": 1738188095.417, "sum(rate(node_network_receive_bytes_total[1m]) + rate(node_network_transmit_bytes_total[1m])) by (instance)": 3618776.6, "network_bytes": 3618776.6, "kubernetes_prometheus_rules": "kubernetes_prometheus_rules", "add_security_context": "add_security_context", "delay_treatment": "delay_treatment"}, {"instance": "kube-prometheus-prometheus-node-exporter.oxn-external-monitoring.svc:9100", "timestamp": 1738188096.417, "sum(rate(node_network_receive_bytes_total[1m]) + rate(node_network_transmit_bytes_total[1m])) by (instance)": 3618776.6, "network_bytes": 3618776.6, "kubernetes_prometheus_rules": "kubernetes_prometheus_rules", "add_security_context": "add_security_context", "delay_treatment": "delay_treatment"}, {"instance": "kube-prometheus-prometheus-node-exporter.oxn-external-monitoring.svc:9100", "timestamp": 1738188097.417, "sum(rate(node_network_receive_bytes_total[1m]) + rate(node_network_transmit_bytes_total[1m])) by (instance)": 3618776.6, "network_bytes": 3618776.6, "kubernetes_prometheus_rules": "kubernetes_prometheus_rules", "add_security_context": "add_security_context", "delay_treatment": "delay_treatment"}, {"instance": "kube-prometheus-prometheus-node-exporter.oxn-external-monitoring.svc:9100", "timestamp": 1738188098.417, "sum(rate(node_network_receive_bytes_total[1m]) + rate(node_network_transmit_bytes_total[1m])) by (instance)": 3618776.6, "network_bytes": 3618776.6, "kubernetes_prometheus_rules": "kubernetes_prometheus_rules", "add_security_context": "add_security_context", "delay_treatment": "delay_treatment"}, {"instance": "kube-prometheus-prometheus-node-exporter.oxn-external-monitoring.svc:9100", "timestamp": 1738188099.417, "sum(rate(node_network_receive_bytes_total[1m]) + rate(node_network_transmit_bytes_total[1m])) by (instance)": 3618776.6, "network_bytes": 3618776.6, "kubernetes_prometheus_rules": "kubernetes_prometheus_rules", "add_security_context": "add_security_context", "delay_treatment": "delay_treatment"}, {"instance": "kube-prometheus-prometheus-node-exporter.oxn-external-monitoring.svc:9100", "timestamp": 1738188100.417, "sum(rate(node_network_receive_bytes_total[1m]) + rate(node_network_transmit_bytes_total[1m])) by (instance)": 3578181.8727272726, "network_bytes": 3578181.8727272726, "kubernetes_prometheus_rules": "kubernetes_prometheus_rules", "add_security_context": "add_security_context", "delay_treatment": "delay_treatment"}, {"instance": "kube-prometheus-prometheus-node-exporter.oxn-external-monitoring.svc:9100", "timestamp": 1738188101.417, "sum(rate(node_network_receive_bytes_total[1m]) + rate(node_network_transmit_bytes_total[1m])) by (instance)": 3578181.8727272726, "network_bytes": 3578181.8727272726, "kubernetes_prometheus_rules": "kubernetes_prometheus_rules", "add_security_context": "add_security_context", "delay_treatment": "delay_treatment"}, {"instance": "kube-prometheus-prometheus-node-exporter.oxn-external-monitoring.svc:9100", "timestamp": 1738188102.417, "sum(rate(node_network_receive_bytes_total[1m]) + rate(node_network_transmit_bytes_total[1m])) by (instance)": 3578181.8727272726, "network_bytes": 3578181.8727272726, "kubernetes_prometheus_rules": "kubernetes_prometheus_rules", "add_security_context": "add_security_context", "delay_treatment": "delay_treatment"}, {"instance": "kube-prometheus-prometheus-node-exporter.oxn-external-monitoring.svc:9100", "timestamp": 1738188103.417, "sum(rate(node_network_receive_bytes_total[1m]) + rate(node_network_transmit_bytes_total[1m])) by (instance)": 3578181.8727272726, "network_bytes": 3578181.8727272726, "kubernetes_prometheus_rules": "kubernetes_prometheus_rules", "add_security_context": "add_security_context", "delay_treatment": "delay_treatment"}, {"instance": "kube-prometheus-prometheus-node-exporter.oxn-external-monitoring.svc:9100", "timestamp": 1738188104.417, "sum(rate(node_network_receive_bytes_total[1m]) + rate(node_network_transmit_bytes_total[1m])) by (instance)": 3578181.8727272726, "network_bytes": 3578181.8727272726, "kubernetes_prometheus_rules": "kubernetes_prometheus_rules", "add_security_context": "add_security_context", "delay_treatment": "delay_treatment"}, {"instance": "kube-prometheus-prometheus-node-exporter.oxn-external-monitoring.svc:9100", "timestamp": 1738188105.417, "sum(rate(node_network_receive_bytes_total[1m]) + rate(node_network_transmit_bytes_total[1m])) by (instance)": 3632391.2363636363, "network_bytes": 3632391.2363636363, "kubernetes_prometheus_rules": "kubernetes_prometheus_rules", "add_security_context": "add_security_context", "delay_treatment": "delay_treatment"}, {"instance": "kube-prometheus-prometheus-node-exporter.oxn-external-monitoring.svc:9100", "timestamp": 1738188106.417, "sum(rate(node_network_receive_bytes_total[1m]) + rate(node_network_transmit_bytes_total[1m])) by (instance)": 3632391.2363636363, "network_bytes": 3632391.2363636363, "kubernetes_prometheus_rules": "kubernetes_prometheus_rules", "add_security_context": "add_security_context", "delay_treatment": "delay_treatment"}, {"instance": "kube-prometheus-prometheus-node-exporter.oxn-external-monitoring.svc:9100", "timestamp": 1738188107.417, "sum(rate(node_network_receive_bytes_total[1m]) + rate(node_network_transmit_bytes_total[1m])) by (instance)": 3632391.2363636363, "network_bytes": 3632391.2363636363, "kubernetes_prometheus_rules": "kubernetes_prometheus_rules", "add_security_context": "add_security_context", "delay_treatment": "delay_treatment"}, {"instance": "kube-prometheus-prometheus-node-exporter.oxn-external-monitoring.svc:9100", "timestamp": 1738188108.417, "sum(rate(node_network_receive_bytes_total[1m]) + rate(node_network_transmit_bytes_total[1m])) by (instance)": 3632391.2363636363, "network_bytes": 3632391.2363636363, "kubernetes_prometheus_rules": "kubernetes_prometheus_rules", "add_security_context": "add_security_context", "delay_treatment": "delay_treatment"}, {"instance": "kube-prometheus-prometheus-node-exporter.oxn-external-monitoring.svc:9100", "timestamp": 1738188109.417, "sum(rate(node_network_receive_bytes_total[1m]) + rate(node_network_transmit_bytes_total[1m])) by (instance)": 3632391.2363636363, "network_bytes": 3632391.2363636363, "kubernetes_prometheus_rules": "kubernetes_prometheus_rules", "add_security_context": "add_security_context", "delay_treatment": "delay_treatment"}, {"instance": "kube-prometheus-prometheus-node-exporter.oxn-external-monitoring.svc:9100", "timestamp": 1738188110.417, "sum(rate(node_network_receive_bytes_total[1m]) + rate(node_network_transmit_bytes_total[1m])) by (instance)": 3626580.436363636, "network_bytes": 3626580.436363636, "kubernetes_prometheus_rules": "kubernetes_prometheus_rules", "add_security_context": "add_security_context", "delay_treatment": "delay_treatment"}, {"instance": "kube-prometheus-prometheus-node-exporter.oxn-external-monitoring.svc:9100", "timestamp": 1738188111.417, "sum(rate(node_network_receive_bytes_total[1m]) + rate(node_network_transmit_bytes_total[1m])) by (instance)": 3626580.436363636, "network_bytes": 3626580.436363636, "kubernetes_prometheus_rules": "kubernetes_prometheus_rules", "add_security_context": "add_security_context", "delay_treatment": "delay_treatment"}, {"instance": "kube-prometheus-prometheus-node-exporter.oxn-external-monitoring.svc:9100", "timestamp": 1738188112.417, "sum(rate(node_network_receive_bytes_total[1m]) + rate(node_network_transmit_bytes_total[1m])) by (instance)": 3626580.436363636, "network_bytes": 3626580.436363636, "kubernetes_prometheus_rules": "kubernetes_prometheus_rules", "add_security_context": "add_security_context", "delay_treatment": "delay_treatment"}, {"instance": "kube-prometheus-prometheus-node-exporter.oxn-external-monitoring.svc:9100", "timestamp": 1738188113.417, "sum(rate(node_network_receive_bytes_total[1m]) + rate(node_network_transmit_bytes_total[1m])) by (instance)": 3626580.436363636, "network_bytes": 3626580.436363636, "kubernetes_prometheus_rules": "kubernetes_prometheus_rules", "add_security_context": "add_security_context", "delay_treatment": "delay_treatment"}, {"instance": "kube-prometheus-prometheus-node-exporter.oxn-external-monitoring.svc:9100", "timestamp": 1738188114.417, "sum(rate(node_network_receive_bytes_total[1m]) + rate(node_network_transmit_bytes_total[1m])) by (instance)": 3626580.436363636, "network_bytes": 3626580.436363636, "kubernetes_prometheus_rules": "kubernetes_prometheus_rules", "add_security_context": "add_security_context", "delay_treatment": "delay_treatment"}, {"instance": "kube-prometheus-prometheus-node-exporter.oxn-external-monitoring.svc:9100", "timestamp": 1738188115.417, "sum(rate(node_network_receive_bytes_total[1m]) + rate(node_network_transmit_bytes_total[1m])) by (instance)": 3619642.290909091, "network_bytes": 3619642.290909091, "kubernetes_prometheus_rules": "kubernetes_prometheus_rules", "add_security_context": "add_security_context", "delay_treatment": "delay_treatment"}, {"instance": "kube-prometheus-prometheus-node-exporter.oxn-external-monitoring.svc:9100", "timestamp": 1738188116.417, "sum(rate(node_network_receive_bytes_total[1m]) + rate(node_network_transmit_bytes_total[1m])) by (instance)": 3619642.290909091, "network_bytes": 3619642.290909091, "kubernetes_prometheus_rules": "kubernetes_prometheus_rules", "add_security_context": "add_security_context", "delay_treatment": "delay_treatment"}, {"instance": "kube-prometheus-prometheus-node-exporter.oxn-external-monitoring.svc:9100", "timestamp": 1738188117.417, "sum(rate(node_network_receive_bytes_total[1m]) + rate(node_network_transmit_bytes_total[1m])) by (instance)": 3619642.290909091, "network_bytes": 3619642.290909091, "kubernetes_prometheus_rules": "kubernetes_prometheus_rules", "add_security_context": "add_security_context", "delay_treatment": "delay_treatment"}, {"instance": "kube-prometheus-prometheus-node-exporter.oxn-external-monitoring.svc:9100", "timestamp": 1738188118.417, "sum(rate(node_network_receive_bytes_total[1m]) + rate(node_network_transmit_bytes_total[1m])) by (instance)": 3619642.290909091, "network_bytes": 3619642.290909091, "kubernetes_prometheus_rules": "kubernetes_prometheus_rules", "add_security_context": "add_security_context", "delay_treatment": "delay_treatment"}, {"instance": "kube-prometheus-prometheus-node-exporter.oxn-external-monitoring.svc:9100", "timestamp": 1738188119.417, "sum(rate(node_network_receive_bytes_total[1m]) + rate(node_network_transmit_bytes_total[1m])) by (instance)": 3619642.290909091, "network_bytes": 3619642.290909091, "kubernetes_prometheus_rules": "kubernetes_prometheus_rules", "add_security_context": "add_security_context", "delay_treatment": "delay_treatment"}, {"instance": "kube-prometheus-prometheus-node-exporter.oxn-external-monitoring.svc:9100", "timestamp": 1738188120.417, "sum(rate(node_network_receive_bytes_total[1m]) + rate(node_network_transmit_bytes_total[1m])) by (instance)": 3627962.9636363634, "network_bytes": 3627962.9636363634, "kubernetes_prometheus_rules": "kubernetes_prometheus_rules", "add_security_context": "add_security_context", "delay_treatment": "delay_treatment"}, {"instance": "kube-prometheus-prometheus-node-exporter.oxn-external-monitoring.svc:9100", "timestamp": 1738188121.417, "sum(rate(node_network_receive_bytes_total[1m]) + rate(node_network_transmit_bytes_total[1m])) by (instance)": 3627962.9636363634, "network_bytes": 3627962.9636363634, "kubernetes_prometheus_rules": "kubernetes_prometheus_rules", "add_security_context": "add_security_context", "delay_treatment": "delay_treatment"}, {"instance": "kube-prometheus-prometheus-node-exporter.oxn-external-monitoring.svc:9100", "timestamp": 1738188122.417, "sum(rate(node_network_receive_bytes_total[1m]) + rate(node_network_transmit_bytes_total[1m])) by (instance)": 3627962.9636363634, "network_bytes": 3627962.9636363634, "kubernetes_prometheus_rules": "kubernetes_prometheus_rules", "add_security_context": "add_security_context", "delay_treatment": "delay_treatment"}, {"instance": "kube-prometheus-prometheus-node-exporter.oxn-external-monitoring.svc:9100", "timestamp": 1738188123.417, "sum(rate(node_network_receive_bytes_total[1m]) + rate(node_network_transmit_bytes_total[1m])) by (instance)": 3627962.9636363634, "network_bytes": 3627962.9636363634, "kubernetes_prometheus_rules": "kubernetes_prometheus_rules", "add_security_context": "add_security_context", "delay_treatment": "delay_treatment"}, {"instance": "kube-prometheus-prometheus-node-exporter.oxn-external-monitoring.svc:9100", "timestamp": 1738188124.417, "sum(rate(node_network_receive_bytes_total[1m]) + rate(node_network_transmit_bytes_total[1m])) by (instance)": 3627962.9636363634, "network_bytes": 3627962.9636363634, "kubernetes_prometheus_rules": "kubernetes_prometheus_rules", "add_security_context": "add_security_context", "delay_treatment": "delay_treatment"}, {"instance": "kube-prometheus-prometheus-node-exporter.oxn-external-monitoring.svc:9100", "timestamp": 1738188125.417, "sum(rate(node_network_receive_bytes_total[1m]) + rate(node_network_transmit_bytes_total[1m])) by (instance)": 3607712.109090909, "network_bytes": 3607712.109090909, "kubernetes_prometheus_rules": "kubernetes_prometheus_rules", "add_security_context": "add_security_context", "delay_treatment": "delay_treatment"}, {"instance": "kube-prometheus-prometheus-node-exporter.oxn-external-monitoring.svc:9100", "timestamp": 1738188126.417, "sum(rate(node_network_receive_bytes_total[1m]) + rate(node_network_transmit_bytes_total[1m])) by (instance)": 3607712.109090909, "network_bytes": 3607712.109090909, "kubernetes_prometheus_rules": "kubernetes_prometheus_rules", "add_security_context": "add_security_context", "delay_treatment": "delay_treatment"}, {"instance": "kube-prometheus-prometheus-node-exporter.oxn-external-monitoring.svc:9100", "timestamp": 1738188127.417, "sum(rate(node_network_receive_bytes_total[1m]) + rate(node_network_transmit_bytes_total[1m])) by (instance)": 3607712.109090909, "network_bytes": 3607712.109090909, "kubernetes_prometheus_rules": "kubernetes_prometheus_rules", "add_security_context": "add_security_context", "delay_treatment": "delay_treatment"}, {"instance": "kube-prometheus-prometheus-node-exporter.oxn-external-monitoring.svc:9100", "timestamp": 1738188128.417, "sum(rate(node_network_receive_bytes_total[1m]) + rate(node_network_transmit_bytes_total[1m])) by (instance)": 3607712.109090909, "network_bytes": 3607712.109090909, "kubernetes_prometheus_rules": "kubernetes_prometheus_rules", "add_security_context": "add_security_context", "delay_treatment": "delay_treatment"}, {"instance": "kube-prometheus-prometheus-node-exporter.oxn-external-monitoring.svc:9100", "timestamp": 1738188129.417, "sum(rate(node_network_receive_bytes_total[1m]) + rate(node_network_transmit_bytes_total[1m])) by (instance)": 3607712.109090909, "network_bytes": 3607712.109090909, "kubernetes_prometheus_rules": "kubernetes_prometheus_rules", "add_security_context": "add_security_context", "delay_treatment": "delay_treatment"}, {"instance": "kube-prometheus-prometheus-node-exporter.oxn-external-monitoring.svc:9100", "timestamp": 1738188130.417, "sum(rate(node_network_receive_bytes_total[1m]) + rate(node_network_transmit_bytes_total[1m])) by (instance)": 3576531.054545454, "network_bytes": 3576531.054545454, "kubernetes_prometheus_rules": "kubernetes_prometheus_rules", "add_security_context": "add_security_context", "delay_treatment": "delay_treatment"}, {"instance": "kube-prometheus-prometheus-node-exporter.oxn-external-monitoring.svc:9100", "timestamp": 1738188131.417, "sum(rate(node_network_receive_bytes_total[1m]) + rate(node_network_transmit_bytes_total[1m])) by (instance)": 3576531.054545454, "network_bytes": 3576531.054545454, "kubernetes_prometheus_rules": "kubernetes_prometheus_rules", "add_security_context": "add_security_context", "delay_treatment": "delay_treatment"}, {"instance": "kube-prometheus-prometheus-node-exporter.oxn-external-monitoring.svc:9100", "timestamp": 1738188132.417, "sum(rate(node_network_receive_bytes_total[1m]) + rate(node_network_transmit_bytes_total[1m])) by (instance)": 3576531.054545454, "network_bytes": 3576531.054545454, "kubernetes_prometheus_rules": "kubernetes_prometheus_rules", "add_security_context": "add_security_context", "delay_treatment": "delay_treatment"}, {"instance": "kube-prometheus-prometheus-node-exporter.oxn-external-monitoring.svc:9100", "timestamp": 1738188133.417, "sum(rate(node_network_receive_bytes_total[1m]) + rate(node_network_transmit_bytes_total[1m])) by (instance)": 3576531.054545454, "network_bytes": 3576531.054545454, "kubernetes_prometheus_rules": "kubernetes_prometheus_rules", "add_security_context": "add_security_context", "delay_treatment": "delay_treatment"}, {"instance": "kube-prometheus-prometheus-node-exporter.oxn-external-monitoring.svc:9100", "timestamp": 1738188134.417, "sum(rate(node_network_receive_bytes_total[1m]) + rate(node_network_transmit_bytes_total[1m])) by (instance)": 3576531.054545454, "network_bytes": 3576531.054545454, "kubernetes_prometheus_rules": "kubernetes_prometheus_rules", "add_security_context": "add_security_context", "delay_treatment": "delay_treatment"}, {"instance": "kube-prometheus-prometheus-node-exporter.oxn-external-monitoring.svc:9100", "timestamp": 1738188135.417, "sum(rate(node_network_receive_bytes_total[1m]) + rate(node_network_transmit_bytes_total[1m])) by (instance)": 3608508.9272727272, "network_bytes": 3608508.9272727272, "kubernetes_prometheus_rules": "kubernetes_prometheus_rules", "add_security_context": "add_security_context", "delay_treatment": "delay_treatment"}, {"instance": "kube-prometheus-prometheus-node-exporter.oxn-external-monitoring.svc:9100", "timestamp": 1738188136.417, "sum(rate(node_network_receive_bytes_total[1m]) + rate(node_network_transmit_bytes_total[1m])) by (instance)": 3608508.9272727272, "network_bytes": 3608508.9272727272, "kubernetes_prometheus_rules": "kubernetes_prometheus_rules", "add_security_context": "add_security_context", "delay_treatment": "delay_treatment"}, {"instance": "kube-prometheus-prometheus-node-exporter.oxn-external-monitoring.svc:9100", "timestamp": 1738188137.417, "sum(rate(node_network_receive_bytes_total[1m]) + rate(node_network_transmit_bytes_total[1m])) by (instance)": 3608508.9272727272, "network_bytes": 3608508.9272727272, "kubernetes_prometheus_rules": "kubernetes_prometheus_rules", "add_security_context": "add_security_context", "delay_treatment": "delay_treatment"}, {"instance": "kube-prometheus-prometheus-node-exporter.oxn-external-monitoring.svc:9100", "timestamp": 1738188138.417, "sum(rate(node_network_receive_bytes_total[1m]) + rate(node_network_transmit_bytes_total[1m])) by (instance)": 3608508.9272727272, "network_bytes": 3608508.9272727272, "kubernetes_prometheus_rules": "kubernetes_prometheus_rules", "add_security_context": "add_security_context", "delay_treatment": "delay_treatment"}, {"instance": "kube-prometheus-prometheus-node-exporter.oxn-external-monitoring.svc:9100", "timestamp": 1738188139.417, "sum(rate(node_network_receive_bytes_total[1m]) + rate(node_network_transmit_bytes_total[1m])) by (instance)": 3608508.9272727272, "network_bytes": 3608508.9272727272, "kubernetes_prometheus_rules": "kubernetes_prometheus_rules", "add_security_context": "add_security_context", "delay_treatment": "delay_treatment"}, {"instance": "kube-prometheus-prometheus-node-exporter.oxn-external-monitoring.svc:9100", "timestamp": 1738188140.417, "sum(rate(node_network_receive_bytes_total[1m]) + rate(node_network_transmit_bytes_total[1m])) by (instance)": 3624129.054545454, "network_bytes": 3624129.054545454, "kubernetes_prometheus_rules": "kubernetes_prometheus_rules", "add_security_context": "add_security_context", "delay_treatment": "delay_treatment"}, {"instance": "kube-prometheus-prometheus-node-exporter.oxn-external-monitoring.svc:9100", "timestamp": 1738188141.417, "sum(rate(node_network_receive_bytes_total[1m]) + rate(node_network_transmit_bytes_total[1m])) by (instance)": 3624129.054545454, "network_bytes": 3624129.054545454, "kubernetes_prometheus_rules": "kubernetes_prometheus_rules", "add_security_context": "add_security_context", "delay_treatment": "delay_treatment"}, {"instance": "kube-prometheus-prometheus-node-exporter.oxn-external-monitoring.svc:9100", "timestamp": 1738188142.417, "sum(rate(node_network_receive_bytes_total[1m]) + rate(node_network_transmit_bytes_total[1m])) by (instance)": 3624129.054545454, "network_bytes": 3624129.054545454, "kubernetes_prometheus_rules": "kubernetes_prometheus_rules", "add_security_context": "add_security_context", "delay_treatment": "delay_treatment"}, {"instance": "kube-prometheus-prometheus-node-exporter.oxn-external-monitoring.svc:9100", "timestamp": 1738188143.417, "sum(rate(node_network_receive_bytes_total[1m]) + rate(node_network_transmit_bytes_total[1m])) by (instance)": 3624129.054545454, "network_bytes": 3624129.054545454, "kubernetes_prometheus_rules": "kubernetes_prometheus_rules", "add_security_context": "add_security_context", "delay_treatment": "delay_treatment"}, {"instance": "kube-prometheus-prometheus-node-exporter.oxn-external-monitoring.svc:9100", "timestamp": 1738188144.417, "sum(rate(node_network_receive_bytes_total[1m]) + rate(node_network_transmit_bytes_total[1m])) by (instance)": 3624129.054545454, "network_bytes": 3624129.054545454, "kubernetes_prometheus_rules": "kubernetes_prometheus_rules", "add_security_context": "add_security_context", "delay_treatment": "delay_treatment"}, {"instance": "kube-prometheus-prometheus-node-exporter.oxn-external-monitoring.svc:9100", "timestamp": 1738188145.417, "sum(rate(node_network_receive_bytes_total[1m]) + rate(node_network_transmit_bytes_total[1m])) by (instance)": 3611947.909090909, "network_bytes": 3611947.909090909, "kubernetes_prometheus_rules": "kubernetes_prometheus_rules", "add_security_context": "add_security_context", "delay_treatment": "delay_treatment"}, {"instance": "kube-prometheus-prometheus-node-exporter.oxn-external-monitoring.svc:9100", "timestamp": 1738188146.417, "sum(rate(node_network_receive_bytes_total[1m]) + rate(node_network_transmit_bytes_total[1m])) by (instance)": 3611947.909090909, "network_bytes": 3611947.909090909, "kubernetes_prometheus_rules": "NoTreatment", "add_security_context": "NoTreatment", "delay_treatment": "NoTreatment"}, {"instance": "kube-prometheus-prometheus-node-exporter.oxn-external-monitoring.svc:9100", "timestamp": 1738188147.417, "sum(rate(node_network_receive_bytes_total[1m]) + rate(node_network_transmit_bytes_total[1m])) by (instance)": 3611947.909090909, "network_bytes": 3611947.909090909, "kubernetes_prometheus_rules": "NoTreatment", "add_security_context": "NoTreatment", "delay_treatment": "NoTreatment"}, {"instance": "kube-prometheus-prometheus-node-exporter.oxn-external-monitoring.svc:9100", "timestamp": 1738188148.417, "sum(rate(node_network_receive_bytes_total[1m]) + rate(node_network_transmit_bytes_total[1m])) by (instance)": 3611947.909090909, "network_bytes": 3611947.909090909, "kubernetes_prometheus_rules": "NoTreatment", "add_security_context": "NoTreatment", "delay_treatment": "NoTreatment"}, {"instance": "kube-prometheus-prometheus-node-exporter.oxn-external-monitoring.svc:9100", "timestamp": 1738188149.417, "sum(rate(node_network_receive_bytes_total[1m]) + rate(node_network_transmit_bytes_total[1m])) by (instance)": 3611947.909090909, "network_bytes": 3611947.909090909, "kubernetes_prometheus_rules": "NoTreatment", "add_security_context": "NoTreatment", "delay_treatment": "NoTreatment"}, {"instance": "kube-prometheus-prometheus-node-exporter.oxn-external-monitoring.svc:9100", "timestamp": 1738188150.417, "sum(rate(node_network_receive_bytes_total[1m]) + rate(node_network_transmit_bytes_total[1m])) by (instance)": 3610488.454545454, "network_bytes": 3610488.454545454, "kubernetes_prometheus_rules": "NoTreatment", "add_security_context": "NoTreatment", "delay_treatment": "NoTreatment"}, {"instance": "kube-prometheus-prometheus-node-exporter.oxn-external-monitoring.svc:9100", "timestamp": 1738188151.417, "sum(rate(node_network_receive_bytes_total[1m]) + rate(node_network_transmit_bytes_total[1m])) by (instance)": 3610488.454545454, "network_bytes": 3610488.454545454, "kubernetes_prometheus_rules": "NoTreatment", "add_security_context": "NoTreatment", "delay_treatment": "NoTreatment"}, {"instance": "kube-prometheus-prometheus-node-exporter.oxn-external-monitoring.svc:9100", "timestamp": 1738188152.417, "sum(rate(node_network_receive_bytes_total[1m]) + rate(node_network_transmit_bytes_total[1m])) by (instance)": 3610488.454545454, "network_bytes": 3610488.454545454, "kubernetes_prometheus_rules": "NoTreatment", "add_security_context": "NoTreatment", "delay_treatment": "NoTreatment"}, {"instance": "kube-prometheus-prometheus-node-exporter.oxn-external-monitoring.svc:9100", "timestamp": 1738188153.417, "sum(rate(node_network_receive_bytes_total[1m]) + rate(node_network_transmit_bytes_total[1m])) by (instance)": 3610488.454545454, "network_bytes": 3610488.454545454, "kubernetes_prometheus_rules": "NoTreatment", "add_security_context": "NoTreatment", "delay_treatment": "NoTreatment"}, {"instance": "kube-prometheus-prometheus-node-exporter.oxn-external-monitoring.svc:9100", "timestamp": 1738188154.417, "sum(rate(node_network_receive_bytes_total[1m]) + rate(node_network_transmit_bytes_total[1m])) by (instance)": 3610488.454545454, "network_bytes": 3610488.454545454, "kubernetes_prometheus_rules": "NoTreatment", "add_security_context": "NoTreatment", "delay_treatment": "NoTreatment"}, {"instance": "kube-prometheus-prometheus-node-exporter.oxn-external-monitoring.svc:9100", "timestamp": 1738188155.417, "sum(rate(node_network_receive_bytes_total[1m]) + rate(node_network_transmit_bytes_total[1m])) by (instance)": 3598631.527272727, "network_bytes": 3598631.527272727, "kubernetes_prometheus_rules": "NoTreatment", "add_security_context": "NoTreatment", "delay_treatment": "NoTreatment"}]